scaffound/__init__.py
scaffound/cip.py
scaffound/paths.py
scaffound/scaffolds.py
scaffound-0.0.1.dist-info/licenses/LICENSE
scaffound-0.0.1.dist-info/METADATA
scaffound-0.0.1.dist-info/WHEEL
scaffound-0.0.1.dist-info/top_level.txt
scaffound-0.0.1.dist-info/RECORD
