Metadata-Version: 2.4
Name: scaffound
Version: 0.0.1
Summary: Python implementation of Dompé's 'Molecular Anatomy'
Home-page: https://github.com/OlivierBeq/scaffound
Author: Olivier J. M. Béquignon
Author-email: "olivier.bequignon.maintainer@gmail.com"
Maintainer: Olivier J. M. Béquignon
Maintainer-email: "olivier.bequignon.maintainer@gmail.com"
License: "MIT"
Keywords: molecular anatomy,molecular scaffold,molecular framework,molecular wireframe,cheminformatics
Classifier: Development Status :: 5 - Production/Stable
Classifier: Programming Language :: Python :: 3.12
Classifier: Programming Language :: Python :: 3.11
Requires-Python: >=3.11
License-File: LICENSE
Requires-Dist: rdkit>=2024.3.1
Requires-Dist: numpy>=2.0.0
Requires-Dist: pandas
Provides-Extra: docs
Requires-Dist: sphinx; extra == "docs"
Requires-Dist: sphinx-rtd-theme; extra == "docs"
Requires-Dist: sphinx-autodoc-typehints; extra == "docs"
Provides-Extra: testing
Requires-Dist: pytest; extra == "testing"
Dynamic: license-file
